[{
    "id":"M28d95dfe-974c-4462-bc40-44650c185cf6",
    "title":"Guardians of Galaxy Vol. 3",
    "description":"Our beloved band of misfits are settling into life on Knowhere. But it isn't long before their lives are upended by the echoes of Rocket's turbulent past. Peter Quill, still reeling from the loss of Gamora, must rally his team around him on a dangerous mission to save Rocket's life - a mission that, if not completed successfully, could quite possibly lead to the end of the Guardians as we know them.','2023-05-05',150,'Action,Adventure,Comedy,Scifi','English,Hindi,Tamil,Telugu','USA','James Gunn','Chris Pratt, Zoe Saldana, Dave Baustita, Karen Gillan, Pom Klementieff, Vin Diesel','9.3','https://assets-in.bmscdn.com/iedb/movies/images/mobile/thumbnail/xlarge/guardians-of-the-galaxy-vol-3-et00310794-1683529214.jpg",
    "releaseDate":"2023-05-05",
    "runtime":150,
    "genre":"Action,Adventure,Comedy,Scifi",
    "language":"English,Hindi,Tamil,Telugu",
    "country":"USA",
    "director":"James Gunn",
    "cast":"Chris Pratt, Zoe Saldana, Dave Baustita, Karen Gillan, Pom Klementieff, Vin Diesel",
    "rating":"9.3",
    "posterUrl":"https://assets-in.bmscdn.com/iedb/movies/images/mobile/thumbnail/xlarge/guardians-of-the-galaxy-vol-3-et00310794-1683529214.jpg",
    "trailerUrl":"https://www.youtube.com/watch?v=LH7KPMsN7nw&t=6s"
},
{
    "id":"M3c056f1b-d2b8-4f3e-9a6b-f0ca0e8e51af",
    "title":"Black Panther",
    "description":"After the death of his father Challa returns home to the African nation of Wakanda to take his rightful place as king",
    "releaseDate":"2018-02-16",
    "runtime":134,
    "genre":"Action, Adventure, Sci-Fi",
    "language":"English",
    "country":"USA",
    "director":"Ryan Coogler",
    "cast":"Chadwick Boseman, Michael B. Jordan, Lupita Nyong  Danai Gurira, Martin Freeman",
    "rating":"8.0",
    "posterUrl":"https://m.media-amazon.com/images/I/91ivR8RdFgL._SL1500_.jpg",
    "trailerUrl":"https://www.youtube.com/watch?v=xjDjIWPwcPU"
},
{
    "id":"M9f7be510-052d-4398-8d24-330d7bde158a",
    "title":"Joker",
    "description":"In Gotham City, mentally troubled comedian Arthur Fleck is disregarded and mistreated by society",
    "releaseDate":"2019-10-04",
    "runtime":122,
    "genre":"Crime, Drama, Thriller",
    "language":"English",
    "country":"USA",
    "director":"Todd Phillips",
    "cast":"Joaquin Phoenix, Robert De Niro, Zazie Beetz, Frances Conroy",
    "rating":"8.4",
    "posterUrl":"https://m.media-amazon.com/images/I/71xU6gjK9gL._SL1500_.jpg",
    "trailerUrl":"https://www.youtube.com/watch?v=zAGVQLHvwO"
}]